[
    {
        "Id": 60,
        "name": "Андижон вилояти",
        "districts": [
            {
                "Id": 1,
                "name": "Андижон шаҳри"
            },
            {
                "Id": 2,
                "name": "Андижон тумани"
            },
            {
                "Id": 3,
                "name": "Асака тумани"
            },
            {
                "Id": 4,
                "name": "Балиқчи тумани"
            },
            {
                "Id": 5,
                "name": "Булоқбоши тумани"
            },
            {
                "Id": 6,
                "name": "Бўз тумани"
            },
            {
                "Id": 7,
                "name": "Жалақудуқ тумани"
            },
            {
                "Id": 8,
                "name": "Избосган тумани"
            },
            {
                "Id": 9,
                "name": "Қорасув шаҳри"
            },
            {
                "Id": 10,
                "name": "Қўрғонтепа тумани"
            },
            {
                "Id": 11,
                "name": "Марҳамат тумани"
            },
            {
                "Id": 12,
                "name": "Олтинкўл тумани"
            },
            {
                "Id": 13,
                "name": "Пахтаобод тумани"
            },
            {
                "Id": 14,
                "name": "Улуғнор тумани"
            },
            {
                "Id": 15,
                "name": "Хонабод тумани"
            },
            {
                "Id": 16,
                "name": "Хўжаобод шаҳри"
            },
            {
                "Id": 17,
                "name": "Шахрихон тумани"
            },
            {
                "Id": 18,
                "name": "Асака шаҳри"
            }
        ]
    },
    {
        "Id": 80,
        "name": "Бухоро вилояти",
        "districts": [
            {
                "Id": 19,
                "name": "Бухоро шаҳри"
            },
            {
                "Id": 20,
                "name": "Бухоро тумани"
            },
            {
                "Id": 21,
                "name": "Вобкент тумани"
            },
            {
                "Id": 22,
                "name": "Ғиждувон тумани"
            },
            {
                "Id": 23,
                "name": "Жондор тумани"
            },
            {
                "Id": 24,
                "name": "Когон тумани"
            },
            {
                "Id": 25,
                "name": "Когон шаҳри"
            },
            {
                "Id": 26,
                "name": "Қоракўл тумани"
            },
            {
                "Id": 27,
                "name": "Қоровулбозор тумани"
            },
            {
                "Id": 28,
                "name": "Олот тумани"
            },
            {
                "Id": 29,
                "name": "Пешку тумани"
            },
            {
                "Id": 30,
                "name": "Ромитан тумани"
            },
            {
                "Id": 31,
                "name": "Шофиркон тумани"
            }
        ]
    },
    {
        "Id": 40,
        "name": "Фарғона вилояти",
        "districts": [
            {
                "Id": 32,
                "name": "Бешариқ тумани"
            },
            {
                "Id": 33,
                "name": "Боғдод тумани"
            },
            {
                "Id": 34,
                "name": "Бувайда тумани"
            },
            {
                "Id": 35,
                "name": "Данғара тумани"
            },
            {
                "Id": 36,
                "name": "Ёзёвон тумани"
            },
            {
                "Id": 37,
                "name": "Қува тумани"
            },
            {
                "Id": 38,
                "name": "Қувасой шаҳри"
            },
            {
                "Id": 39,
                "name": "Қўқон шаҳри"
            },
            {
                "Id": 40,
                "name": "Қўштепа тумани"
            },
            {
                "Id": 41,
                "name": "Марғилон шаҳри"
            },
            {
                "Id": 42,
                "name": "Олтиариқ тумани"
            },
            {
                "Id": 43,
                "name": "Риштон тумани"
            },
            {
                "Id": 44,
                "name": "Сўх тумани"
            },
            {
                "Id": 45,
                "name": "Тошлоқ тумани"
            },
            {
                "Id": 46,
                "name": "Учкўприк тумани"
            },
            {
                "Id": 47,
                "name": "Ўзбекистон тумани"
            },
            {
                "Id": 48,
                "name": "Фарғона тумани"
            },
            {
                "Id": 49,
                "name": "Фарғона шаҳри"
            },
            {
                "Id": 50,
                "name": "Фурқат тумани"
            }
        ]
    },
    {
        "Id": 25,
        "name": "Жиззах вилояти",
        "districts": [
            {
                "Id": 51,
                "name": "Арнасой тумани"
            },
            {
                "Id": 52,
                "name": "Бахмал тумани"
            },
            {
                "Id": 53,
                "name": "Ғаллаорол тумани"
            },
            {
                "Id": 54,
                "name": "Дўстлик тумани"
            },
            {
                "Id": 55,
                "name": "Ш.Рашидов тумани"
            },
            {
                "Id": 56,
                "name": "Жиззах шаҳри"
            },
            {
                "Id": 57,
                "name": "Зарбдор тумани"
            },
            {
                "Id": 58,
                "name": "Зафаробод тумани"
            },
            {
                "Id": 59,
                "name": "Зомин тумани"
            },
            {
                "Id": 60,
                "name": "Мирзачўл тумани"
            },
            {
                "Id": 61,
                "name": "Пахтакор тумани"
            },
            {
                "Id": 62,
                "name": "Фориш тумани"
            },
            {
                "Id": 63,
                "name": "Янгиобод тумани"
            }
        ]
    },
    {
        "Id": 50,
        "name": "Наманган вилояти",
        "districts": [
            {
                "Id": 64,
                "name": "Косонсой тумани"
            },
            {
                "Id": 65,
                "name": "Мингбулоқ тумани"
            },
            {
                "Id": 66,
                "name": "Наманган тумани"
            },
            {
                "Id": 67,
                "name": "Наманган шаҳри"
            },
            {
                "Id": 68,
                "name": "Норин тумани"
            },
            {
                "Id": 69,
                "name": "Поп тумани"
            },
            {
                "Id": 70,
                "name": "Тўрақўрғон тумани"
            },
            {
                "Id": 71,
                "name": "Уйчи тумани"
            },
            {
                "Id": 72,
                "name": "Учқўрғон тумани"
            },
            {
                "Id": 73,
                "name": "Чортоқ тумани"
            },
            {
                "Id": 74,
                "name": "Чуст тумани"
            },
            {
                "Id": 75,
                "name": "Янгиқўрғон тумани"
            }
        ]
    },
    {
        "Id": 85,
        "name": "Навоий вилояти",
        "districts": [
            {
                "Id": 76,
                "name": "Зарафшон шаҳри"
            },
            {
                "Id": 77,
                "name": "Кармана тумани"
            },
            {
                "Id": 78,
                "name": "Қизилтепа тумани"
            },
            {
                "Id": 79,
                "name": "Конимех тумани"
            },
            {
                "Id": 80,
                "name": "Навбаҳор тумани"
            },
            {
                "Id": 81,
                "name": "Навоий шаҳри"
            },
            {
                "Id": 82,
                "name": "Нурота тумани"
            },
            {
                "Id": 83,
                "name": "Томди тумани"
            },
            {
                "Id": 84,
                "name": "Учқудуқ тумани"
            },
            {
                "Id": 85,
                "name": "Хатирчи тумани"
            }
        ]
    },
    {
        "Id": 70,
        "name": "Қашқадарё вилояти",
        "districts": [
            {
                "Id": 73,
                "name": "Ғузор тумани"
            },
            {
                "Id": 86,
                "name": "Деҳқонобод тумани"
            },
            {
                "Id": 87,
                "name": "Қамаши тумани"
            },
            {
                "Id": 88,
                "name": "Қарши тумани"
            },
            {
                "Id": 89,
                "name": "Қарши шаҳри"
            },
            {
                "Id": 90,
                "name": "Касби тумани"
            },
            {
                "Id": 91,
                "name": "Китоб тумани"
            },
            {
                "Id": 92,
                "name": "Косон тумани"
            },
            {
                "Id": 93,
                "name": "Миришкор тумани"
            },
            {
                "Id": 94,
                "name": "Муборак тумани"
            },
            {
                "Id": 94,
                "name": "Нишон тумани"
            },
            {
                "Id": 95,
                "name": "Чироқчи тумани"
            },
            {
                "Id": 97,
                "name": "Шаҳрисабз тумани"
            },
            {
                "Id": 98,
                "name": "Яккабоғ тумани"
            },
            {
                "Id": 99,
                "name": "Кўкдала тумани"
            }
        ]
    },
    {
        "Id": 95,
        "name": "Қорақалпоғистон Республикаси",
        "districts": [
            {
                "Id": 100,
                "name": "Амударё тумани"
            },
            {
                "Id": 101,
                "name": "Беруний тумани"
            },
            {
                "Id": 102,
                "name": "Кегайли тумани"
            },
            {
                "Id": 103,
                "name": "Қонликўл тумани"
            },
            {
                "Id": 104,
                "name": "Қораўзак тумани"
            },
            {
                "Id": 105,
                "name": "Қўнғирот тумани"
            },
            {
                "Id": 106,
                "name": "Мўйноқ тумани"
            },
            {
                "Id": 107,
                "name": "Нукус тумани"
            },
            {
                "Id": 108,
                "name": "Нукус шаҳри"
            },
            {
                "Id": 109,
                "name": "Тахтакўпир тумани"
            },
            {
                "Id": 110,
                "name": "Тўрткўл тумани"
            },
            {
                "Id": 111,
                "name": "Хўжайли тумани"
            },
            {
                "Id": 112,
                "name": "Чимбой тумани"
            },
            {
                "Id": 113,
                "name": "Шуманай тумани"
            },
            {
                "Id": 114,
                "name": "Элликқалъа тумани"
            },
            {
                "Id": 115,
                "name": "Тахиатош шаҳри"
            },
            {
                "Id": 116,
                "name": "Бўзатов тумани"
            }
        ]
    },
    {
        "Id": 30,
        "name": "Самарқанд вилояти",
        "districts": [
            {
                "Id": 117,
                "name": "Булунғур тумани"
            },
            {
                "Id": 118,
                "name": "Жомбой тумани"
            },
            {
                "Id": 119,
                "name": "Иштихон тумани"
            },
            {
                "Id": 120,
                "name": "Каттақўрғон тумани"
            },
            {
                "Id": 121,
                "name": "Каттақўрғон шаҳри"
            },
            {
                "Id": 122,
                "name": "Қўшработ тумани"
            },
            {
                "Id": 123,
                "name": "Нарпай тумани"
            },
            {
                "Id": 124,
                "name": "Нурабод тумани"
            },
            {
                "Id": 125,
                "name": "Оқдарё тумани"
            },
            {
                "Id": 126,
                "name": "Паяриқ тумани"
            },
            {
                "Id": 127,
                "name": "Пастарғом тумани"
            },
            {
                "Id": 128,
                "name": "Пахтачи тумани"
            },
            {
                "Id": 129,
                "name": "Самарқанд тумани"
            },
            {
                "Id": 130,
                "name": "Самарқанд шаҳри"
            },
            {
                "Id": 131,
                "name": "Тойлоқ тумани"
            },
            {
                "Id": 132,
                "name": "Ургут тумани"
            }
        ]
    },
    {
        "Id": 20,
        "name": "Сирдарё вилояти",
        "districts": [
            {
                "Id": 133,
                "name": "Боёвут тумани"
            },
            {
                "Id": 134,
                "name": "Гулистон тумани"
            },
            {
                "Id": 135,
                "name": "Гулистон шаҳри"
            },
            {
                "Id": 136,
                "name": "Мирзаобод тумани"
            },
            {
                "Id": 137,
                "name": "Оқолтин тумани"
            },
            {
                "Id": 138,
                "name": "Сайхунобод тумани"
            },
            {
                "Id": 139,
                "name": "Сардоба тумани"
            },
            {
                "Id": 140,
                "name": "Сирдарё тумани"
            },
            {
                "Id": 141,
                "name": "Хавос тумани"
            },
            {
                "Id": 142,
                "name": "Ширин шаҳри"
            },
            {
                "Id": 143,
                "name": "Янгиэр шаҳри"
            }
        ]
    },
    {
        "Id": 75,
        "name": "Сурхандарё вилояти",
        "districts": [
            {
                "Id": 144,
                "name": "Ангор тумани"
            },
            {
                "Id": 145,
                "name": "Бойсун тумани"
            },
            {
                "Id": 146,
                "name": "Денов тумани"
            },
            {
                "Id": 147,
                "name": "Жарқўрғон тумани"
            },
            {
                "Id": 148,
                "name": "Қизириқ тумани"
            },
            {
                "Id": 149,
                "name": "Қўмқўрғон тумани"
            },
            {
                "Id": 150,
                "name": "Музработ тумани"
            },
            {
                "Id": 151,
                "name": "Олтинсой тумани"
            },
            {
                "Id": 152,
                "name": "Сариосий тумани"
            },
            {
                "Id": 153,
                "name": "Термиз тумани"
            },
            {
                "Id": 154,
                "name": "Термиз шаҳри"
            },
            {
                "Id": 155,
                "name": "Узун тумани"
            },
            {
                "Id": 156,
                "name": "Шеробод тумани"
            },
            {
                "Id": 157,
                "name": "Шўрчи тумани"
            },
            {
                "Id": 158,
                "name": "Бандихон тумани"
            }
        ]
    },
    {
        "Id": 1,
        "name": "Тошкент шаҳри",
        "districts": [
            {
                "Id": 159,
                "name": "Бектимер тумани"
            },
            {
                "Id": 160,
                "name": "М.Улуғбек тумани"
            },
            {
                "Id": 170,
                "name": "Миробод тумани"
            },
            {
                "Id": 171,
                "name": "Олмазор тумани"
            },
            {
                "Id": 172,
                "name": "Сергели тумани"
            },
            {
                "Id": 173,
                "name": "Учтепа тумани"
            },
            {
                "Id": 174,
                "name": "Яшнобод тумани"
            },
            {
                "Id": 175,
                "name": "Чилонзор тумани"
            },
            {
                "Id": 176,
                "name": "Шайхонтоҳур тумани"
            },
            {
                "Id": 177,
                "name": "Юнусобод тумани"
            },
            {
                "Id": 178,
                "name": "Яккасарой тумани"
            }
        ]
    },
    {
        "Id": 10,
        "name": "Тошкент вилояти",
        "districts": [
            {
                "Id": 179,
                "name": "Ангирен шаҳри"
            },
            {
                "Id": 180,
                "name": "Бекабод тумани"
            },
            {
                "Id": 181,
                "name": "Бекабод шаҳри"
            },
            {
                "Id": 182,
                "name": "Бўка тумани"
            },
            {
                "Id": 183,
                "name": "Бўстонлиқ тумани"
            },
            {
                "Id": 184,
                "name": "Зангиота тумани"
            },
            {
                "Id": 185,
                "name": "Қибрай тумани"
            },
            {
                "Id": 186,
                "name": "Қуйичирчиқ тумани"
            },
            {
                "Id": 187,
                "name": "Оққўрғон тумани"
            },
            {
                "Id": 188,
                "name": "Олмалиқ шаҳри"
            },
            {
                "Id": 189,
                "name": "Оҳангарон тумани"
            },
            {
                "Id": 190,
                "name": "Паркент тумани"
            },
            {
                "Id": 191,
                "name": "Пискент тумани"
            },
            {
                "Id": 192,
                "name": "Ўртачирчиқ тумани"
            },
            {
                "Id": 193,
                "name": "Чиноз тумани"
            },
            {
                "Id": 194,
                "name": "Чирчиқ шаҳри"
            },
            {
                "Id": 195,
                "name": "Юқоричирчиқ тумани"
            },
            {
                "Id": 196,
                "name": "Янгийўл тумани"
            },
            {
                "Id": 197,
                "name": "Оҳангарон шаҳри"
            },
            {
                "Id": 198,
                "name": "Янгийўл шаҳри"
            },
            {
                "Id": 199,
                "name": "Тошкент тумани"
            }
        ]
    },
    {
        "Id": 90,
        "name": "Хоразм вилояти",
        "districts": [
            {
                "Id": 200,
                "name": "Боғот тумани"
            },
            {
                "Id": 201,
                "name": "Гурлан тумани"
            },
            {
                "Id": 202,
                "name": "Қўшкўпир тумани"
            },
            {
                "Id": 203,
                "name": "Урганч тумани"
            },
            {
                "Id": 204,
                "name": "Урганч шаҳри"
            },
            {
                "Id": 205,
                "name": "Хива тумани"
            },
            {
                "Id": 206,
                "name": "Хазарасп тумани"
            },
            {
                "Id": 207,
                "name": "Хонқа тумани"
            },
            {
                "Id": 208,
                "name": "Шавот тумани"
            },
            {
                "Id": 209,
                "name": "Янгиариқ тумани"
            },
            {
                "Id": 210,
                "name": "Янгибозор тумани"
            },
            {
                "Id": 211,
                "name": "Тупроққала тумани"
            }
        ]
    }
]